fft_conv_pytorch/__init__.py
fft_conv_pytorch/fft_conv.py
fft_conv_pytorch/utils.py
fft_conv_pytorch-1.2.0.dist-info/LICENSE
fft_conv_pytorch-1.2.0.dist-info/METADATA
fft_conv_pytorch-1.2.0.dist-info/WHEEL
fft_conv_pytorch-1.2.0.dist-info/top_level.txt
fft_conv_pytorch-1.2.0.dist-info/RECORD
