Metadata-Version: 2.1
Name: fft-conv-pytorch
Version: 1.2.0
Summary: Implementation of 1D, 2D, and 3D FFT convolutions in PyTorch.
Home-page: https://github.com/fkodom/fft-conv-pytorch
Author: Frank Odom
Author-email: frank.odom.iii@gmail.com
Classifier: Programming Language :: Python :: 3
Classifier: Operating System :: OS Independent
Requires-Python: >=3.7
License-File: LICENSE
Requires-Dist: numpy
Requires-Dist: torch>=1.8
Provides-Extra: test
Requires-Dist: black; extra == "test"
Requires-Dist: flake8; extra == "test"
Requires-Dist: isort; extra == "test"
Requires-Dist: pytest; extra == "test"
Requires-Dist: pytest-cov; extra == "test"
